madcore-1.9.65-py2.7-nspkg.pth
madcore/cmd.py
madcore/cmdhelm.py
madcore/cmdkops.py
madcore/cmdkubectl.py
madcore/cmdminikube.py
madcore/cybermedium.flf
madcore/elements.py
madcore/localtemplate.py
madcore/madcore.py
madcore/provision.py
madcore/settings.py
madcore/static.py
madcore/clusters/demo.yaml
madcore/clusters/minikube.yaml
madcore/clusters/solvezone.yaml
madcore/templates/kops.1.9.0.cluster.yaml
madcore/templates/kops.1.9.0.ig.yaml
madcore/templates/kops.1.9.0.master.yaml
madcore/templates/kubectl.101.dashboard.yaml
madcore/templates/kubectl.102.route53.yaml
madcore/templates/kubectl.111.ingress-default-deployment.yaml
madcore/templates/kubectl.112.http-svc-deployment.yaml
madcore/templates/kubectl.121.storage-ns.yaml
madcore/templates/kubectl.122.storage-local-provisioner.yaml
madcore/templates/kubectl.123.storage-local-class.yaml
madcore/templates/kubectl.127.storage-nfs-provisioner.yaml
madcore/templates/kubectl.128.storage-nfs-class.yaml
madcore/templates/kubectl.141.registry.yaml
madcore/templates/kubectl.142.ingress.service.registry.yaml
madcore/templates/kubectl.151.influxdb.yaml
madcore/templates/kubectl.152.heapster.yaml
madcore/templates/kubectl.153.grafana.yaml
madcore/templates/kubectl.154.grafana.ing.yaml
madcore/templates/kubectl.171.haproxy-configmap.yaml
madcore/templates/kubectl.172.haproxy-ingress-deployment.yaml
madcore/templates/kubectl.173.haproxy-ingress-svc.yaml
madcore/templates/kubectl.174.http-svc-ingress.yaml
madcore/templates/kubectl.9000.cert-manager.yaml
madcore/templates/kubectl.9100.keycloak.yaml
madcore/templates/kubectl.9101.keycloak.cert.yaml
madcore/templates/kubectl.9102.keycloak.ingress.yaml
madcore/templates/kubectl.9103.keycloak.namespace.yaml
madcore/templates/kubectl.9201.elasticsearch.yaml
madcore/templates/kubectl.9202.fluentd.yaml
madcore/templates/kubectl.9203.kibana.yaml
madcore/templates/kubectl.9204.oauth2-proxy.yaml
madcore-1.9.65.dist-info/LICENSE.txt
madcore-1.9.65.dist-info/METADATA
madcore-1.9.65.dist-info/RECORD
madcore-1.9.65.dist-info/WHEEL
madcore-1.9.65.dist-info/entry_points.txt
madcore-1.9.65.dist-info/namespace_packages.txt
madcore-1.9.65.dist-info/top_level.txt
