Metadata-Version: 2.1
Name: madcore
Version: 1.9.65
Summary: Madcore Core CLI - Deep Learning & Machine Intelligence Infrastructure Controller
Home-page: https://github.com/madcore-ai/cli
Author: Peter Styk
Author-email: humans@madcore.ai
License: MIT
Download-URL: https://github.com/madcore-ai/cli/tarball/master
Keywords: aws,infrastructure,kubernetes,cluster,machine learning,gpu
Platform: Any
Classifier: Development Status :: 3 - Alpha
Classifier: License :: OSI Approved :: MIT License
Classifier: Programming Language :: Python :: 2.7
Classifier: Intended Audience :: Developers
Classifier: Environment :: Console
Requires-Dist: termcolor (==1.1.0)
Requires-Dist: Jinja2 (==2.9.6)
Requires-Dist: yamlordereddictloader (==0.4.0)
Requires-Dist: pyOpenSSL (==16.2.0)
Requires-Dist: urllib3 (==1.22)
Requires-Dist: prettytable (==0.7.2)
Requires-Dist: requests (==2.18.4)
